[
  {
    "id": 1,
    "name": "Propri\u00e9taire Maison 1",
    "email": "maison1@smartcas.ma",
    "password": "demo123",
    "address": "Quartier Maarif, Casablanca - Maison 1",
    "household_id": 1
  },
  {
    "id": 2,
    "name": "Propri\u00e9taire Maison 2",
    "email": "maison2@smartcas.ma",
    "password": "demo123",
    "address": "Quartier Maarif, Casablanca - Maison 2",
    "household_id": 2
  },
  {
    "id": 3,
    "name": "Propri\u00e9taire Maison 3",
    "email": "maison3@smartcas.ma",
    "password": "demo123",
    "address": "Quartier Maarif, Casablanca - Maison 3",
    "household_id": 3
  },
  {
    "id": 4,
    "name": "Propri\u00e9taire Maison 4",
    "email": "maison4@smartcas.ma",
    "password": "demo123",
    "address": "Quartier Maarif, Casablanca - Maison 4",
    "household_id": 4
  },
  {
    "id": 5,
    "name": "Propri\u00e9taire Maison 5",
    "email": "maison5@smartcas.ma",
    "password": "demo123",
    "address": "Quartier Maarif, Casablanca - Maison 5",
    "household_id": 5
  }
]